__init__.py
cluster_challenge/_version.py
cluster_challenge/matching/clevar_matching.py
cluster_challenge/matching/cosmoDC2_skysim5000_matching.py
cluster_challenge/performance/comparison.py
cluster_challenge/performance/completeness.py
cluster_challenge/performance/mass_richness.py
cluster_challenge/performance/richness_mass_parametrization.py
cluster_challenge/performance/selection_function.py
cluster_challenge/performance/selection_function_halos.py
cluster_challenge/performance/selection_function_halos_closure.py
cluster_challenge/performance/selection_function_halos_global_fit.py
cluster_challenge/performance/selection_function_redmapper_global_fit.py
cluster_challenge/performance/selection_functions.py
cluster_challenge/performance/make_plots/make_plots.py
cluster_challenge/performance/make_plots/plotting_functions.py
cluster_challenge/pre_processing/flexzboost_cosmoDC2.py
cluster_challenge/pre_processing/galaxy_selection.py
cluster_challenge/pre_processing/galaxy_selection_flexzboost.py
cluster_challenge/pre_processing/param_mstar.py
cluster_challenge/pre_processing/photoz_validation.py
cluster_challenge/pre_processing/stack.py
cluster_challenge/pre_processing/training_check.py
cluster_challenge/prepare_catalogs/opening_catalogs_functions.py
cluster_challenge/prepare_catalogs/read_amico.cosmoDC2.fzb.py
cluster_challenge/prepare_catalogs/read_amico.cosmoDC2.py
cluster_challenge/prepare_catalogs/read_cosmoDC2.py
cluster_challenge/prepare_catalogs/read_redmapper.DC2.py
cluster_challenge/prepare_catalogs/read_redmapper.cosmoDC2.py
cluster_challenge/prepare_catalogs/read_wazp.DC2.py
cluster_challenge/prepare_catalogs/read_wazp.cosmoDC2.fzb.py
cluster_challenge/prepare_catalogs/read_wazp.cosmoDC2.py
cluster_challenge/validation/comparison.py
cluster_challenge/validation/cosmoDC2_studies.py
cluster_challenge/validation/footprint.py
cluster_challenge-0.0.1.dev0.dist-info/METADATA
cluster_challenge-0.0.1.dev0.dist-info/WHEEL
cluster_challenge-0.0.1.dev0.dist-info/top_level.txt
cluster_challenge-0.0.1.dev0.dist-info/RECORD
